octodns_dyn/__init__.py
octodns_dyn-0.0.1.dist-info/METADATA
octodns_dyn-0.0.1.dist-info/WHEEL
octodns_dyn-0.0.1.dist-info/top_level.txt
octodns_dyn-0.0.1.dist-info/RECORD
