Metadata-Version: 2.1
Name: octodns-dyn
Version: 0.0.1
Summary: [DEPRECATED] DynProvider provider for octoDNS
Home-page: https://github.com/octodns/octodns-dyn
Author: Ross McFarland
Author-email: rwmcfa1@gmail.com
License: MIT
Platform: UNKNOWN
Requires-Python: >=3.6
Requires-Dist: octodns (>=0.9.14)
Requires-Dist: dyn (==1.8.1)
